Mornay/Mornay.py
Mornay/__init__.py
Mornay/example.py
Mornay-0.0.1.dist-info/METADATA
Mornay-0.0.1.dist-info/WHEEL
Mornay-0.0.1.dist-info/entry_points.txt
Mornay-0.0.1.dist-info/top_level.txt
Mornay-0.0.1.dist-info/RECORD
